manimgl_mathjax/__init__.py
manimgl_mathjax/index.js
manimgl_mathjax/installer.py
manimgl_mathjax/mathjax.py
manimgl_mathjax/package.json
manimgl_mathjax/tex2svg.js
manimgl_mathjax-0.1.1.dist-info/LICENSE.md
manimgl_mathjax-0.1.1.dist-info/METADATA
manimgl_mathjax-0.1.1.dist-info/WHEEL
manimgl_mathjax-0.1.1.dist-info/entry_points.txt
manimgl_mathjax-0.1.1.dist-info/top_level.txt
manimgl_mathjax-0.1.1.dist-info/RECORD
