Metadata-Version: 2.1
Name: manimgl-mathjax
Version: 0.1.1
Summary: A plugin for ManimGL with tex2svg renderer using mathjax
Home-page: https://github.com/manim-kindergarten/ManimGL-MathJax
Author: Manim Kindergarten Team
License: MIT
Project-URL: Bug Tracker, https://github.com/manim-kindergarten/ManimGL-MathJax/issues
Project-URL: Source Code, https://github.com/manim-kindergarten/ManimGL-MathJax/
Platform: UNKNOWN
Classifier: Development Status :: 3 - Alpha
Classifier: License :: OSI Approved :: MIT License
Classifier: Topic :: Scientific/Engineering
Classifier: Topic :: Multimedia :: Video
Classifier: Topic :: Multimedia :: Graphics
Classifier: Programming Language :: Python :: 3.6
Classifier: Programming Language :: Python :: 3.7
Classifier: Programming Language :: Python :: 3.8
Classifier: Programming Language :: Python :: 3.9
Classifier: Programming Language :: Python :: 3.10
Classifier: Programming Language :: Python :: 3 :: Only
Classifier: Programming Language :: JavaScript
Requires-Dist: manimgl (>=1.5.0)
